future/__init__.py
future/backports/__init__.py
future/backports/_markupbase.py
future/backports/datetime.py
future/backports/misc.py
future/backports/socket.py
future/backports/socketserver.py
future/backports/total_ordering.py
future/backports/email/__init__.py
future/backports/email/_encoded_words.py
future/backports/email/_header_value_parser.py
future/backports/email/_parseaddr.py
future/backports/email/_policybase.py
future/backports/email/base64mime.py
future/backports/email/charset.py
future/backports/email/encoders.py
future/backports/email/errors.py
future/backports/email/feedparser.py
future/backports/email/generator.py
future/backports/email/header.py
future/backports/email/headerregistry.py
future/backports/email/iterators.py
future/backports/email/message.py
future/backports/email/parser.py
future/backports/email/policy.py
future/backports/email/quoprimime.py
future/backports/email/utils.py
future/backports/email/mime/__init__.py
future/backports/email/mime/application.py
future/backports/email/mime/audio.py
future/backports/email/mime/base.py
future/backports/email/mime/image.py
future/backports/email/mime/message.py
future/backports/email/mime/multipart.py
future/backports/email/mime/nonmultipart.py
future/backports/email/mime/text.py
future/backports/html/__init__.py
future/backports/html/entities.py
future/backports/html/parser.py
future/backports/http/__init__.py
future/backports/http/client.py
future/backports/http/cookiejar.py
future/backports/http/cookies.py
future/backports/http/server.py
future/backports/test/__init__.py
future/backports/test/badcert.pem
future/backports/test/badkey.pem
future/backports/test/dh512.pem
future/backports/test/https_svn_python_org_root.pem
future/backports/test/keycert.passwd.pem
future/backports/test/keycert.pem
future/backports/test/keycert2.pem
future/backports/test/nokia.pem
future/backports/test/nullbytecert.pem
future/backports/test/nullcert.pem
future/backports/test/pystone.py
future_nodefix-0.17.0.dist-info/LICENSE.txt
future_nodefix-0.17.0.dist-info/METADATA
future_nodefix-0.17.0.dist-info/WHEEL
future_nodefix-0.17.0.dist-info/entry_points.txt
future_nodefix-0.17.0.dist-info/top_level.txt
future_nodefix-0.17.0.dist-info/RECORD
